{
    "image_id": "IMG_8856",
    "width": 2592,
    "height": 1728,
    "coco_id": null,
    "flickr_id": null,
    "objects": [
        {
            "object_id": 7,
            "x": 1295.5,
            "y": 1394.7777709960938,
            "w": 2591.0,
            "h": 664.4444580078125,
            "names": [
                "floor"
            ],
            "synsets": []
        },
        {
            "object_id": 5,
            "x": 2414.5,
            "y": 542.388916015625,
            "w": 353.0,
            "h": 1084.77783203125,
            "names": [
                "door"
            ],
            "synsets": []
        },
        {
            "object_id": 4,
            "x": 1132.0625,
            "y": 544.611083984375,
            "w": 2264.125,
            "h": 1089.22216796875,
            "names": [
                "wall"
            ],
            "synsets": []
        },
        {
            "object_id": 20,
            "x": 657.1428833007812,
            "y": 1024.6666564941406,
            "w": 1314.2857666015625,
            "h": 782.6666870117188,
            "names": [
                "staircase"
            ],
            "synsets": []
        },
        {
            "object_id": 17,
            "x": 1321.2406005859375,
            "y": 712.0300903320312,
            "w": 174.06005859375,
            "h": 111.2781982421875,
            "names": [
                "handrail"
            ],
            "synsets": []
        }
    ],
    "relationships": [
        {
            "subject_id": 5,
            "object_id": 4,
            "predicate": "has opening in",
            "relationship_id": 9
        },
        {
            "subject_id": 20,
            "object_id": 17,
            "predicate": "equipped with",
            "relationship_id": 12
        }
    ]
}