{
    "image_id": "IMG_8770",
    "width": 2592,
    "height": 1728,
    "coco_id": null,
    "flickr_id": null,
    "objects": [
        {
            "object_id": 7,
            "x": 1295.5,
            "y": 1553.5,
            "w": 2591.0,
            "h": 347.0,
            "names": [
                "floor"
            ],
            "synsets": []
        },
        {
            "object_id": 5,
            "x": 2199.5,
            "y": 729.0,
            "w": 783.0,
            "h": 1458.0,
            "names": [
                "door"
            ],
            "synsets": []
        },
        {
            "object_id": 4,
            "x": 924.1666870117188,
            "y": 730.7222290039062,
            "w": 1848.3333740234375,
            "h": 1461.4444580078125,
            "names": [
                "wall"
            ],
            "synsets": []
        },
        {
            "object_id": 14,
            "x": 1677.669921875,
            "y": 713.5922241210938,
            "w": 151.456298828125,
            "h": 64.07763671875,
            "names": [
                "light switch"
            ],
            "synsets": []
        },
        {
            "object_id": 11,
            "x": 968.75,
            "y": 358.75,
            "w": 657.5,
            "h": 585.0,
            "names": [
                "board"
            ],
            "synsets": []
        },
        {
            "object_id": 13,
            "x": 1708.8636474609375,
            "y": 312.72727966308594,
            "w": 103.181884765625,
            "h": 112.72726440429688,
            "names": [
                "door sign"
            ],
            "synsets": []
        }
    ],
    "relationships": [
        {
            "subject_id": 5,
            "object_id": 4,
            "predicate": "has opening in",
            "relationship_id": 9
        },
        {
            "subject_id": 14,
            "object_id": 4,
            "predicate": "mounted on",
            "relationship_id": 2
        },
        {
            "subject_id": 11,
            "object_id": 4,
            "predicate": "fixed on",
            "relationship_id": 13
        }
    ]
}