{"image_id": "IMG_8853", "width": 2592, "height": 1728, "coco_id": null, "flickr_id": null, "objects": [{"object_id": 1, "x": 1295.5, "y": 777.5, "w": 2591.0, "h": 1555.0, "names": ["ceiling"], "synsets": []}, {"object_id": 4, "x": 1295.5, "y": 1399.5, "w": 2591.0, "h": 655.0, "names": ["wall"], "synsets": []}, {"object_id": 4, "x": 177.75, "y": 89.75, "w": 354.5, "h": 179.5, "names": ["wall"], "synsets": []}, {"object_id": 6, "x": 1873.6842041015625, "y": 740.7894592285156, "w": 77.443603515625, "h": 56.76690673828125, "names": ["smoke alarm"], "synsets": []}, {"object_id": 6, "x": 2491.54931640625, "y": 951.5258178710938, "w": 55.86865234375, "h": 54.225341796875, "names": ["smoke alarm"], "synsets": []}, {"object_id": 20, "x": 596.1785888671875, "y": 484.5714285373688, "w": 1192.357177734375, "h": 958.8571429252625, "names": ["staircase"], "synsets": []}]}